simplefuzzyset/__init__.py
simplefuzzyset-0.0.12.dist-info/DESCRIPTION.rst
simplefuzzyset-0.0.12.dist-info/METADATA
simplefuzzyset-0.0.12.dist-info/RECORD
simplefuzzyset-0.0.12.dist-info/WHEEL
simplefuzzyset-0.0.12.dist-info/metadata.json
simplefuzzyset-0.0.12.dist-info/top_level.txt
