Metadata-Version: 2.0
Name: simplefuzzyset
Version: 0.0.12
Summary: A simpler python fuzzyset implementation.
Home-page: https://github.com/morinted/fuzzyset/
Author: Theodore Morin
Author-email: morinted@gmail.com
License: BSD
Keywords: fuzzyset fuzzy data structure
Platform: UNKNOWN
Classifier: Development Status :: 3 - Alpha
Classifier: License :: OSI Approved :: BSD License
Classifier: Operating System :: OS Independent
Classifier: Programming Language :: Python
Classifier: Topic :: Software Development :: Libraries
